zyjj_spider/__init__.py
zyjj_spider/base/__init__.py
zyjj_spider/base/base.py
zyjj_spider/base/exception.py
zyjj_spider/spider/__init__.py
zyjj_spider/spider/base/__init__.py
zyjj_spider/spider/base/spider.py
zyjj_spider/spider/base/utils.py
zyjj_spider/spider/bilibili/__init__.py
zyjj_spider/spider/bilibili/bilibili_test.py
zyjj_spider/spider/bilibili/example.txt
zyjj_spider/spider/bilibili/utils.py
zyjj_spider/spider/douyin/__init__.py
zyjj_spider/spider/douyin/abogus.py
zyjj_spider/spider/douyin/douyin_test.py
zyjj_spider/spider/douyin/example.txt
zyjj_spider/spider/douyin/utils.py
zyjj_spider/spider/douyin/xbogus.py
zyjj_spider/utils/__init__.py
zyjj_spider-1.0.2.dist-info/METADATA
zyjj_spider-1.0.2.dist-info/WHEEL
zyjj_spider-1.0.2.dist-info/RECORD
