Metadata-Version: 2.1
Name: zyjj-spider
Version: 1.0.2
Summary: 
Author: xiaoyou
Author-email: xiaoyou2333@foxmail.com
Requires-Python: >=3.12,<4.0
Classifier: Programming Language :: Python :: 3
Classifier: Programming Language :: Python :: 3.12
Classifier: Programming Language :: Python :: 3.13
Requires-Dist: gmssl (>=3.2.2,<4.0.0)
Requires-Dist: httpx (>=0.28.1,<0.29.0)
